notifications_tui/__init__.py
notifications_tui/main.py
clipboard_tui-1.0.0.dist-info/LICENSE
clipboard_tui-1.0.0.dist-info/METADATA
clipboard_tui-1.0.0.dist-info/WHEEL
clipboard_tui-1.0.0.dist-info/entry_points.txt
clipboard_tui-1.0.0.dist-info/top_level.txt
clipboard_tui-1.0.0.dist-info/RECORD
