Metadata-Version: 2.1
Name: clipboard-tui
Version: 1.0.0
Summary: TUI application for clipboard history
Home-page: https://github.com/mile95/notifications-tui
Author: Fredrik Mile
Author-email: fredrik.mile@gmail.com
License: MIT
License-File: LICENSE
Requires-Dist: pyperclip (==1.8.2)
